getoptify/__init__.py
getoptify/__main__.py
getoptify-1.1.2.dist-info/LICENSE.txt
getoptify-1.1.2.dist-info/METADATA
getoptify-1.1.2.dist-info/WHEEL
getoptify-1.1.2.dist-info/top_level.txt
getoptify-1.1.2.dist-info/RECORD
