Metadata-Version: 2.1
Name: getoptify
Version: 1.1.2
Summary: getoptify
Author-email: Johannes <johannes-programming@mailfence.com>
License: The MIT License (MIT)
Project-URL: Documentation, https://pypi.org/project/getoptify
Project-URL: Download, https://pypi.org/project/getoptify/#files
Project-URL: Source, https://github.com/johannes-programming/getoptify
Classifier: License :: OSI Approved :: MIT License
Classifier: Programming Language :: Python
Classifier: Programming Language :: Python :: 3
Classifier: Programming Language :: Python :: 3 :: Only
Requires-Python: >=3.12.4
License-File: LICENSE.txt
